{"title":"算法设计与分析-课后练习28","uid":"0b8d67f8201f5b754862328905883ea3","slug":"算法设计与分析-课后练习28","date":"2023-12-20T06:01:28.000Z","updated":"2023-12-20T14:02:13.122Z","comments":true,"path":"api/articles/算法设计与分析-课后练习28.json","keywords":"记录, 学习, ClaRnS","cover":"/gallery/algo.png","content":"<h1 id=\"课后练习28\"><a href=\"#课后练习28\" class=\"headerlink\" title=\"课后练习28\"></a>课后练习28</h1><img src=\"../gallery/algo/课后练习28.png\" width=\"750\">\n\n\n<div class=\"language-python\"><button title=\"Copy code\" class=\"copy\"></button><span class=\"lang\">python</span><pre class=\"shiki vitesse-dark\" style=\"background-color: #1a1a1a\" tabindex=\"0\"><code><span class=\"line\"><span style=\"color: #DBD7CAEE\">orders </span><span style=\"color: #666666\">=</span><span style=\"color: #DBD7CAEE\"> </span><span style=\"color: #666666\">&#123;</span></span>\n<span class=\"line\"><span style=\"color: #DBD7CAEE\">    </span><span style=\"color: #C98A7D99\">&#39;</span><span style=\"color: #C98A7D\">q_0</span><span style=\"color: #C98A7D99\">&#39;</span><span style=\"color: #666666\">:[</span></span>\n<span class=\"line\"><span style=\"color: #DBD7CAEE\">        </span><span style=\"color: #666666\">(</span><span style=\"color: #C98A7D99\">&#39;</span><span style=\"color: #C98A7D\">q_0</span><span style=\"color: #C98A7D99\">&#39;</span><span style=\"color: #666666\">,</span><span style=\"color: #DBD7CAEE\"> </span><span style=\"color: #C98A7D99\">&#39;</span><span style=\"color: #C98A7D\">0</span><span style=\"color: #C98A7D99\">&#39;</span><span style=\"color: #666666\">,</span><span style=\"color: #DBD7CAEE\"> </span><span style=\"color: #C98A7D99\">&#39;</span><span style=\"color: #C98A7D\">1</span><span style=\"color: #C98A7D99\">&#39;</span><span style=\"color: #666666\">,</span><span style=\"color: #DBD7CAEE\"> </span><span style=\"color: #C98A7D99\">&#39;</span><span style=\"color: #C98A7D\">L</span><span style=\"color: #C98A7D99\">&#39;</span><span style=\"color: #666666\">,</span><span style=\"color: #DBD7CAEE\"> </span><span style=\"color: #C98A7D99\">&#39;</span><span style=\"color: #C98A7D\">q_1</span><span style=\"color: #C98A7D99\">&#39;</span><span style=\"color: #666666\">),</span></span>\n<span class=\"line\"><span style=\"color: #DBD7CAEE\">        </span><span style=\"color: #666666\">(</span><span style=\"color: #C98A7D99\">&#39;</span><span style=\"color: #C98A7D\">q_0</span><span style=\"color: #C98A7D99\">&#39;</span><span style=\"color: #666666\">,</span><span style=\"color: #DBD7CAEE\"> </span><span style=\"color: #C98A7D99\">&#39;</span><span style=\"color: #C98A7D\">1</span><span style=\"color: #C98A7D99\">&#39;</span><span style=\"color: #666666\">,</span><span style=\"color: #DBD7CAEE\"> </span><span style=\"color: #C98A7D99\">&#39;</span><span style=\"color: #C98A7D\">0</span><span style=\"color: #C98A7D99\">&#39;</span><span style=\"color: #666666\">,</span><span style=\"color: #DBD7CAEE\"> </span><span style=\"color: #C98A7D99\">&#39;</span><span style=\"color: #C98A7D\">L</span><span style=\"color: #C98A7D99\">&#39;</span><span style=\"color: #666666\">,</span><span style=\"color: #DBD7CAEE\"> </span><span style=\"color: #C98A7D99\">&#39;</span><span style=\"color: #C98A7D\">q_2</span><span style=\"color: #C98A7D99\">&#39;</span><span style=\"color: #666666\">),</span></span>\n<span class=\"line\"><span style=\"color: #DBD7CAEE\">        </span><span style=\"color: #666666\">(</span><span style=\"color: #C98A7D99\">&#39;</span><span style=\"color: #C98A7D\">q_0</span><span style=\"color: #C98A7D99\">&#39;</span><span style=\"color: #666666\">,</span><span style=\"color: #DBD7CAEE\"> </span><span style=\"color: #C98A7D99\">&#39;</span><span style=\"color: #C98A7D\">B</span><span style=\"color: #C98A7D99\">&#39;</span><span style=\"color: #666666\">,</span><span style=\"color: #DBD7CAEE\"> </span><span style=\"color: #C98A7D99\">&#39;</span><span style=\"color: #C98A7D\">B</span><span style=\"color: #C98A7D99\">&#39;</span><span style=\"color: #666666\">,</span><span style=\"color: #DBD7CAEE\"> </span><span style=\"color: #C98A7D99\">&#39;</span><span style=\"color: #C98A7D\">H</span><span style=\"color: #C98A7D99\">&#39;</span><span style=\"color: #666666\">,</span><span style=\"color: #DBD7CAEE\"> </span><span style=\"color: #C98A7D99\">&#39;</span><span style=\"color: #C98A7D\">q_F</span><span style=\"color: #C98A7D99\">&#39;</span><span style=\"color: #666666\">)</span></span>\n<span class=\"line\"><span style=\"color: #DBD7CAEE\">    </span><span style=\"color: #666666\">],</span></span>\n<span class=\"line\"><span style=\"color: #DBD7CAEE\">    </span><span style=\"color: #C98A7D99\">&#39;</span><span style=\"color: #C98A7D\">q_1</span><span style=\"color: #C98A7D99\">&#39;</span><span style=\"color: #666666\">:[</span></span>\n<span class=\"line\"><span style=\"color: #DBD7CAEE\">        </span><span style=\"color: #666666\">(</span><span style=\"color: #C98A7D99\">&#39;</span><span style=\"color: #C98A7D\">q_1</span><span style=\"color: #C98A7D99\">&#39;</span><span style=\"color: #666666\">,</span><span style=\"color: #DBD7CAEE\"> </span><span style=\"color: #C98A7D99\">&#39;</span><span style=\"color: #C98A7D\">0</span><span style=\"color: #C98A7D99\">&#39;</span><span style=\"color: #666666\">,</span><span style=\"color: #DBD7CAEE\"> </span><span style=\"color: #C98A7D99\">&#39;</span><span style=\"color: #C98A7D\">0</span><span style=\"color: #C98A7D99\">&#39;</span><span style=\"color: #666666\">,</span><span style=\"color: #DBD7CAEE\"> </span><span style=\"color: #C98A7D99\">&#39;</span><span style=\"color: #C98A7D\">L</span><span style=\"color: #C98A7D99\">&#39;</span><span style=\"color: #666666\">,</span><span style=\"color: #DBD7CAEE\"> </span><span style=\"color: #C98A7D99\">&#39;</span><span style=\"color: #C98A7D\">q_1</span><span style=\"color: #C98A7D99\">&#39;</span><span style=\"color: #666666\">),</span></span>\n<span class=\"line\"><span style=\"color: #DBD7CAEE\">        </span><span style=\"color: #666666\">(</span><span style=\"color: #C98A7D99\">&#39;</span><span style=\"color: #C98A7D\">q_1</span><span style=\"color: #C98A7D99\">&#39;</span><span style=\"color: #666666\">,</span><span style=\"color: #DBD7CAEE\"> </span><span style=\"color: #C98A7D99\">&#39;</span><span style=\"color: #C98A7D\">1</span><span style=\"color: #C98A7D99\">&#39;</span><span style=\"color: #666666\">,</span><span style=\"color: #DBD7CAEE\"> </span><span style=\"color: #C98A7D99\">&#39;</span><span style=\"color: #C98A7D\">1</span><span style=\"color: #C98A7D99\">&#39;</span><span style=\"color: #666666\">,</span><span style=\"color: #DBD7CAEE\"> </span><span style=\"color: #C98A7D99\">&#39;</span><span style=\"color: #C98A7D\">L</span><span style=\"color: #C98A7D99\">&#39;</span><span style=\"color: #666666\">,</span><span style=\"color: #DBD7CAEE\"> </span><span style=\"color: #C98A7D99\">&#39;</span><span style=\"color: #C98A7D\">q_1</span><span style=\"color: #C98A7D99\">&#39;</span><span style=\"color: #666666\">),</span></span>\n<span class=\"line\"><span style=\"color: #DBD7CAEE\">        </span><span style=\"color: #666666\">(</span><span style=\"color: #C98A7D99\">&#39;</span><span style=\"color: #C98A7D\">q_1</span><span style=\"color: #C98A7D99\">&#39;</span><span style=\"color: #666666\">,</span><span style=\"color: #DBD7CAEE\"> </span><span style=\"color: #C98A7D99\">&#39;</span><span style=\"color: #C98A7D\">B</span><span style=\"color: #C98A7D99\">&#39;</span><span style=\"color: #666666\">,</span><span style=\"color: #DBD7CAEE\"> </span><span style=\"color: #C98A7D99\">&#39;</span><span style=\"color: #C98A7D\">B</span><span style=\"color: #C98A7D99\">&#39;</span><span style=\"color: #666666\">,</span><span style=\"color: #DBD7CAEE\"> </span><span style=\"color: #C98A7D99\">&#39;</span><span style=\"color: #C98A7D\">H</span><span style=\"color: #C98A7D99\">&#39;</span><span style=\"color: #666666\">,</span><span style=\"color: #DBD7CAEE\"> </span><span style=\"color: #C98A7D99\">&#39;</span><span style=\"color: #C98A7D\">q_F</span><span style=\"color: #C98A7D99\">&#39;</span><span style=\"color: #666666\">)</span></span>\n<span class=\"line\"><span style=\"color: #DBD7CAEE\">    </span><span style=\"color: #666666\">],</span></span>\n<span class=\"line\"><span style=\"color: #DBD7CAEE\">    </span><span style=\"color: #C98A7D99\">&#39;</span><span style=\"color: #C98A7D\">q_2</span><span style=\"color: #C98A7D99\">&#39;</span><span style=\"color: #666666\">:[</span></span>\n<span class=\"line\"><span style=\"color: #DBD7CAEE\">        </span><span style=\"color: #666666\">(</span><span style=\"color: #C98A7D99\">&#39;</span><span style=\"color: #C98A7D\">q_0</span><span style=\"color: #C98A7D99\">&#39;</span><span style=\"color: #666666\">,</span><span style=\"color: #DBD7CAEE\"> </span><span style=\"color: #C98A7D99\">&#39;</span><span style=\"color: #C98A7D\">0</span><span style=\"color: #C98A7D99\">&#39;</span><span style=\"color: #666666\">,</span><span style=\"color: #DBD7CAEE\"> </span><span style=\"color: #C98A7D99\">&#39;</span><span style=\"color: #C98A7D\">1</span><span style=\"color: #C98A7D99\">&#39;</span><span style=\"color: #666666\">,</span><span style=\"color: #DBD7CAEE\"> </span><span style=\"color: #C98A7D99\">&#39;</span><span style=\"color: #C98A7D\">L</span><span style=\"color: #C98A7D99\">&#39;</span><span style=\"color: #666666\">,</span><span style=\"color: #DBD7CAEE\"> </span><span style=\"color: #C98A7D99\">&#39;</span><span style=\"color: #C98A7D\">q_1</span><span style=\"color: #C98A7D99\">&#39;</span><span style=\"color: #666666\">),</span></span>\n<span class=\"line\"><span style=\"color: #DBD7CAEE\">        </span><span style=\"color: #666666\">(</span><span style=\"color: #C98A7D99\">&#39;</span><span style=\"color: #C98A7D\">q_0</span><span style=\"color: #C98A7D99\">&#39;</span><span style=\"color: #666666\">,</span><span style=\"color: #DBD7CAEE\"> </span><span style=\"color: #C98A7D99\">&#39;</span><span style=\"color: #C98A7D\">1</span><span style=\"color: #C98A7D99\">&#39;</span><span style=\"color: #666666\">,</span><span style=\"color: #DBD7CAEE\"> </span><span style=\"color: #C98A7D99\">&#39;</span><span style=\"color: #C98A7D\">0</span><span style=\"color: #C98A7D99\">&#39;</span><span style=\"color: #666666\">,</span><span style=\"color: #DBD7CAEE\"> </span><span style=\"color: #C98A7D99\">&#39;</span><span style=\"color: #C98A7D\">L</span><span style=\"color: #C98A7D99\">&#39;</span><span style=\"color: #666666\">,</span><span style=\"color: #DBD7CAEE\"> </span><span style=\"color: #C98A7D99\">&#39;</span><span style=\"color: #C98A7D\">q_2</span><span style=\"color: #C98A7D99\">&#39;</span><span style=\"color: #666666\">),</span></span>\n<span class=\"line\"><span style=\"color: #DBD7CAEE\">        </span><span style=\"color: #666666\">(</span><span style=\"color: #C98A7D99\">&#39;</span><span style=\"color: #C98A7D\">q_0</span><span style=\"color: #C98A7D99\">&#39;</span><span style=\"color: #666666\">,</span><span style=\"color: #DBD7CAEE\"> </span><span style=\"color: #C98A7D99\">&#39;</span><span style=\"color: #C98A7D\">B</span><span style=\"color: #C98A7D99\">&#39;</span><span style=\"color: #666666\">,</span><span style=\"color: #DBD7CAEE\"> </span><span style=\"color: #C98A7D99\">&#39;</span><span style=\"color: #C98A7D\">B</span><span style=\"color: #C98A7D99\">&#39;</span><span style=\"color: #666666\">,</span><span style=\"color: #DBD7CAEE\"> </span><span style=\"color: #C98A7D99\">&#39;</span><span style=\"color: #C98A7D\">H</span><span style=\"color: #C98A7D99\">&#39;</span><span style=\"color: #666666\">,</span><span style=\"color: #DBD7CAEE\"> </span><span style=\"color: #C98A7D99\">&#39;</span><span style=\"color: #C98A7D\">q_F</span><span style=\"color: #C98A7D99\">&#39;</span><span style=\"color: #666666\">)</span></span>\n<span class=\"line\"><span style=\"color: #DBD7CAEE\">    </span><span style=\"color: #666666\">],</span></span>\n<span class=\"line\"><span style=\"color: #DBD7CAEE\">    </span><span style=\"color: #C98A7D99\">&#39;</span><span style=\"color: #C98A7D\">q_F</span><span style=\"color: #C98A7D99\">&#39;</span><span style=\"color: #666666\">:[</span></span>\n<span class=\"line\"><span style=\"color: #DBD7CAEE\">        </span></span>\n<span class=\"line\"><span style=\"color: #DBD7CAEE\">    </span><span style=\"color: #666666\">],</span></span>\n<span class=\"line\"><span style=\"color: #666666\">&#125;</span></span>\n<span class=\"line\"></span>\n<span class=\"line\"><span style=\"color: #CB7676\">def</span><span style=\"color: #DBD7CAEE\"> </span><span style=\"color: #80A665\">turing_machine</span><span style=\"color: #666666\">(</span><span style=\"color: #DBD7CAEE\">data</span><span style=\"color: #666666\">):</span></span>\n<span class=\"line\"><span style=\"color: #DBD7CAEE\">    current_state </span><span style=\"color: #666666\">=</span><span style=\"color: #DBD7CAEE\"> </span><span style=\"color: #C98A7D99\">&#39;</span><span style=\"color: #C98A7D\">q_0</span><span style=\"color: #C98A7D99\">&#39;</span></span>\n<span class=\"line\"><span style=\"color: #DBD7CAEE\">    output </span><span style=\"color: #666666\">=</span><span style=\"color: #DBD7CAEE\"> </span><span style=\"color: #666666\">[</span><span style=\"color: #C98A7D99\">&#39;</span><span style=\"color: #C98A7D\">B</span><span style=\"color: #C98A7D99\">&#39;</span><span style=\"color: #666666\">]</span></span>\n<span class=\"line\"><span style=\"color: #DBD7CAEE\">    i </span><span style=\"color: #666666\">=</span><span style=\"color: #DBD7CAEE\"> </span><span style=\"color: #4C9A91\">1</span></span>\n<span class=\"line\"><span style=\"color: #DBD7CAEE\">    </span><span style=\"color: #4D9375\">while</span><span style=\"color: #DBD7CAEE\"> current_state </span><span style=\"color: #CB7676\">!=</span><span style=\"color: #DBD7CAEE\"> </span><span style=\"color: #C98A7D99\">&#39;</span><span style=\"color: #C98A7D\">q_F</span><span style=\"color: #C98A7D99\">&#39;</span><span style=\"color: #666666\">:</span></span>\n<span class=\"line\"><span style=\"color: #DBD7CAEE\">        index </span><span style=\"color: #666666\">=</span><span style=\"color: #DBD7CAEE\"> </span><span style=\"color: #B8A965\">len</span><span style=\"color: #666666\">(</span><span style=\"color: #DBD7CAEE\">data</span><span style=\"color: #666666\">)</span><span style=\"color: #CB7676\">-</span><span style=\"color: #DBD7CAEE\">i</span><span style=\"color: #CB7676\">-</span><span style=\"color: #4C9A91\">1</span></span>\n<span class=\"line\"><span style=\"color: #DBD7CAEE\">        order_group </span><span style=\"color: #666666\">=</span><span style=\"color: #DBD7CAEE\"> orders</span><span style=\"color: #666666\">[</span><span style=\"color: #DBD7CAEE\">current_state</span><span style=\"color: #666666\">]</span></span>\n<span class=\"line\"><span style=\"color: #DBD7CAEE\">        </span><span style=\"color: #4D9375\">for</span><span style=\"color: #DBD7CAEE\"> order </span><span style=\"color: #4D9375\">in</span><span style=\"color: #DBD7CAEE\"> order_group</span><span style=\"color: #666666\">:</span></span>\n<span class=\"line\"><span style=\"color: #DBD7CAEE\">            </span><span style=\"color: #4D9375\">if</span><span style=\"color: #DBD7CAEE\"> order</span><span style=\"color: #666666\">[</span><span style=\"color: #4C9A91\">1</span><span style=\"color: #666666\">]</span><span style=\"color: #DBD7CAEE\"> </span><span style=\"color: #CB7676\">==</span><span style=\"color: #DBD7CAEE\"> data</span><span style=\"color: #666666\">[</span><span style=\"color: #DBD7CAEE\">index</span><span style=\"color: #666666\">]:</span></span>\n<span class=\"line\"><span style=\"color: #DBD7CAEE\">                output</span><span style=\"color: #666666\">.</span><span style=\"color: #DBD7CAEE\">append</span><span style=\"color: #666666\">(</span><span style=\"color: #DBD7CAEE\">order</span><span style=\"color: #666666\">[</span><span style=\"color: #4C9A91\">2</span><span style=\"color: #666666\">])</span></span>\n<span class=\"line\"><span style=\"color: #DBD7CAEE\">                current_state </span><span style=\"color: #666666\">=</span><span style=\"color: #DBD7CAEE\"> order</span><span style=\"color: #666666\">[</span><span style=\"color: #CB7676\">-</span><span style=\"color: #4C9A91\">1</span><span style=\"color: #666666\">]</span></span>\n<span class=\"line\"><span style=\"color: #DBD7CAEE\">                </span><span style=\"color: #4D9375\">if</span><span style=\"color: #DBD7CAEE\"> order</span><span style=\"color: #666666\">[</span><span style=\"color: #4C9A91\">3</span><span style=\"color: #666666\">]</span><span style=\"color: #DBD7CAEE\"> </span><span style=\"color: #CB7676\">==</span><span style=\"color: #DBD7CAEE\"> </span><span style=\"color: #C98A7D99\">&#39;</span><span style=\"color: #C98A7D\">L</span><span style=\"color: #C98A7D99\">&#39;</span><span style=\"color: #666666\">:</span></span>\n<span class=\"line\"><span style=\"color: #DBD7CAEE\">                    i </span><span style=\"color: #666666\">+=</span><span style=\"color: #DBD7CAEE\"> </span><span style=\"color: #4C9A91\">1</span></span>\n<span class=\"line\"><span style=\"color: #DBD7CAEE\">                </span><span style=\"color: #4D9375\">elif</span><span style=\"color: #DBD7CAEE\"> order</span><span style=\"color: #666666\">[</span><span style=\"color: #4C9A91\">3</span><span style=\"color: #666666\">]</span><span style=\"color: #DBD7CAEE\"> </span><span style=\"color: #CB7676\">==</span><span style=\"color: #DBD7CAEE\"> </span><span style=\"color: #C98A7D99\">&#39;</span><span style=\"color: #C98A7D\">H</span><span style=\"color: #C98A7D99\">&#39;</span><span style=\"color: #666666\">:</span></span>\n<span class=\"line\"><span style=\"color: #DBD7CAEE\">                    </span><span style=\"color: #4D9375\">pass</span></span>\n<span class=\"line\"><span style=\"color: #DBD7CAEE\">    </span></span>\n<span class=\"line\"><span style=\"color: #DBD7CAEE\">    output</span><span style=\"color: #666666\">.</span><span style=\"color: #DBD7CAEE\">reverse</span><span style=\"color: #666666\">()</span></span>\n<span class=\"line\"><span style=\"color: #DBD7CAEE\">    </span><span style=\"color: #4D9375\">return</span><span style=\"color: #DBD7CAEE\"> </span><span style=\"color: #C98A7D99\">&#39;&#39;</span><span style=\"color: #666666\">.</span><span style=\"color: #DBD7CAEE\">join</span><span style=\"color: #666666\">(</span><span style=\"color: #DBD7CAEE\">output</span><span style=\"color: #666666\">)</span></span></code></pre></div><div class=\"language-python\"><button title=\"Copy code\" class=\"copy\"></button><span class=\"lang\">python</span><pre class=\"shiki vitesse-dark\" style=\"background-color: #1a1a1a\" tabindex=\"0\"><code><span class=\"line\"><span style=\"color: #DBD7CAEE\">data </span><span style=\"color: #666666\">=</span><span style=\"color: #DBD7CAEE\"> </span><span style=\"color: #C98A7D99\">&#39;</span><span style=\"color: #C98A7D\">B10100010B</span><span style=\"color: #C98A7D99\">&#39;</span></span>\n<span class=\"line\"><span style=\"color: #DBD7CAEE\">output_str </span><span style=\"color: #666666\">=</span><span style=\"color: #DBD7CAEE\"> turing_machine</span><span style=\"color: #666666\">(</span><span style=\"color: #DBD7CAEE\">data</span><span style=\"color: #666666\">)</span></span>\n<span class=\"line\"><span style=\"color: #B8A965\">print</span><span style=\"color: #666666\">(</span><span style=\"color: #C98A7D99\">&#39;</span><span style=\"color: #C99076\">%s</span><span style=\"color: #C98A7D\"> 按照指令执行后得到的结果为 </span><span style=\"color: #C99076\">%s</span><span style=\"color: #C98A7D99\">&#39;</span><span style=\"color: #DBD7CAEE\"> </span><span style=\"color: #CB7676\">%</span><span style=\"color: #DBD7CAEE\"> </span><span style=\"color: #666666\">(</span><span style=\"color: #DBD7CAEE\">data</span><span style=\"color: #666666\">,</span><span style=\"color: #DBD7CAEE\"> output_str</span><span style=\"color: #666666\">))</span></span></code></pre></div><div class=\"language-txt\"><button title=\"Copy code\" class=\"copy\"></button><span class=\"lang\">txt</span><pre class=\"shiki vitesse-dark\" style=\"background-color: #1a1a1a\" tabindex=\"0\"><code><span class=\"line\"><span style=\"color: #dbd7caee\">B10100010B 按照指令执行后得到的结果为 B10100011B</span></span></code></pre></div><div class=\"language-python\"><button title=\"Copy code\" class=\"copy\"></button><span class=\"lang\">python</span><pre class=\"shiki vitesse-dark\" style=\"background-color: #1a1a1a\" tabindex=\"0\"><code><span class=\"line\"><span style=\"color: #DBD7CAEE\">data </span><span style=\"color: #666666\">=</span><span style=\"color: #DBD7CAEE\"> </span><span style=\"color: #C98A7D99\">&#39;</span><span style=\"color: #C98A7D\">B10100011B</span><span style=\"color: #C98A7D99\">&#39;</span></span>\n<span class=\"line\"><span style=\"color: #DBD7CAEE\">output_str </span><span style=\"color: #666666\">=</span><span style=\"color: #DBD7CAEE\"> turing_machine</span><span style=\"color: #666666\">(</span><span style=\"color: #DBD7CAEE\">data</span><span style=\"color: #666666\">)</span></span>\n<span class=\"line\"><span style=\"color: #B8A965\">print</span><span style=\"color: #666666\">(</span><span style=\"color: #C98A7D99\">&#39;</span><span style=\"color: #C99076\">%s</span><span style=\"color: #C98A7D\"> 按照指令执行后得到的结果为 </span><span style=\"color: #C99076\">%s</span><span style=\"color: #C98A7D99\">&#39;</span><span style=\"color: #DBD7CAEE\"> </span><span style=\"color: #CB7676\">%</span><span style=\"color: #DBD7CAEE\"> </span><span style=\"color: #666666\">(</span><span style=\"color: #DBD7CAEE\">data</span><span style=\"color: #666666\">,</span><span style=\"color: #DBD7CAEE\"> output_str</span><span style=\"color: #666666\">))</span></span></code></pre></div><div class=\"language-txt\"><button title=\"Copy code\" class=\"copy\"></button><span class=\"lang\">txt</span><pre class=\"shiki vitesse-dark\" style=\"background-color: #1a1a1a\" tabindex=\"0\"><code><span class=\"line\"><span style=\"color: #dbd7caee\">B10100011B 按照指令执行后得到的结果为 B10100100B</span></span></code></pre></div><div class=\"language-python\"><button title=\"Copy code\" class=\"copy\"></button><span class=\"lang\">python</span><pre class=\"shiki vitesse-dark\" style=\"background-color: #1a1a1a\" tabindex=\"0\"><code><span class=\"line\"></span></code></pre></div>","text":"课后练习28 pythonorders = &#123; &#39;q_0&#39;:[ (&#39;q_0&#39;, &#39;0&#39;, &#39;1...","permalink":"/post/算法设计与分析-课后练习28","photos":[],"count_time":{"symbolsCount":"1.8k","symbolsTime":"2 mins."},"categories":[{"name":"基础","slug":"基础","count":35,"path":"api/categories/基础.json"},{"name":"作业","slug":"基础/作业","count":23,"path":"api/categories/基础/作业.json"},{"name":"算法","slug":"基础/作业/算法","count":23,"path":"api/categories/基础/作业/算法.json"}],"tags":[{"name":"作业","slug":"作业","count":26,"path":"api/tags/作业.json"},{"name":"算法","slug":"算法","count":25,"path":"api/tags/算法.json"}],"toc":"<ol class=\"toc\"><li class=\"toc-item toc-level-1\"><a class=\"toc-link\" href=\"#%E8%AF%BE%E5%90%8E%E7%BB%83%E4%B9%A028\"><span class=\"toc-text\">课后练习28</span></a></li></ol>","author":{"name":"ClaRn","slug":"blog-author","avatar":"/gallery/avatar.jpg","link":"/","description":"当你在浪费时间的事情里获得了快乐，那就不是在浪费时间。 ——罗素","socials":{"github":"https://github.com/iYIYiYIYi","twitter":"","stackoverflow":"","wechat":"","qq":"","weibo":"","zhihu":"","csdn":"","juejin":"","customs":{}}},"mapped":true,"hidden":false,"prev_post":{"title":"算法设计与分析-课后练习27","uid":"599eb923a29a4703289f1f5bf9c3c6e4","slug":"算法设计与分析-课后练习27","date":"2023-12-20T06:03:08.000Z","updated":"2023-12-20T14:03:33.018Z","comments":true,"path":"api/articles/算法设计与分析-课后练习27.json","keywords":"记录, 学习, ClaRnS","cover":"/gallery/algo.png","text":"课后练习27 pythontext = &#39;ababcabccabccacbab&#39; pattern = &#39;abccac&#39;pytho...","permalink":"/post/算法设计与分析-课后练习27","photos":[],"count_time":{"symbolsCount":"4.7k","symbolsTime":"4 mins."},"categories":[{"name":"基础","slug":"基础","count":35,"path":"api/categories/基础.json"},{"name":"作业","slug":"基础/作业","count":23,"path":"api/categories/基础/作业.json"},{"name":"算法","slug":"基础/作业/算法","count":23,"path":"api/categories/基础/作业/算法.json"}],"tags":[{"name":"作业","slug":"作业","count":26,"path":"api/tags/作业.json"},{"name":"算法","slug":"算法","count":25,"path":"api/tags/算法.json"}],"author":{"name":"ClaRn","slug":"blog-author","avatar":"/gallery/avatar.jpg","link":"/","description":"当你在浪费时间的事情里获得了快乐，那就不是在浪费时间。 ——罗素","socials":{"github":"https://github.com/iYIYiYIYi","twitter":"","stackoverflow":"","wechat":"","qq":"","weibo":"","zhihu":"","csdn":"","juejin":"","customs":{}}}},"next_post":{"title":"算法设计与分析-算法实现5","uid":"b7f65afed6da02513803114eb0a78e80","slug":"算法设计与分析-算法实现5","date":"2023-12-10T23:09:35.000Z","updated":"2023-12-11T07:09:54.729Z","comments":true,"path":"api/articles/算法设计与分析-算法实现5.json","keywords":"记录, 学习, ClaRnS","cover":"/gallery/algo.png","text":"算法实现5 pythoninput_data = [1,2,3,7] def solve_24(nums): # 用于计算两数运算结果的函数 def calcu...","permalink":"/post/算法设计与分析-算法实现5","photos":[],"count_time":{"symbolsCount":"1.9k","symbolsTime":"2 mins."},"categories":[{"name":"基础","slug":"基础","count":35,"path":"api/categories/基础.json"},{"name":"作业","slug":"基础/作业","count":23,"path":"api/categories/基础/作业.json"},{"name":"算法","slug":"基础/作业/算法","count":23,"path":"api/categories/基础/作业/算法.json"}],"tags":[{"name":"作业","slug":"作业","count":26,"path":"api/tags/作业.json"},{"name":"算法","slug":"算法","count":25,"path":"api/tags/算法.json"}],"author":{"name":"ClaRn","slug":"blog-author","avatar":"/gallery/avatar.jpg","link":"/","description":"当你在浪费时间的事情里获得了快乐，那就不是在浪费时间。 ——罗素","socials":{"github":"https://github.com/iYIYiYIYi","twitter":"","stackoverflow":"","wechat":"","qq":"","weibo":"","zhihu":"","csdn":"","juejin":"","customs":{}}}}}